{
    "swagger": "2.0",
    "info": {
        "description": "This is a backend API for Image Service",
        "title": "Image Upload API",
        "contact": {},
        "version": "1.0"
    },
    "host": "127.0.0.1:8080",
    "basePath": "/api/",
    "paths": {
        "/images/{id}": {
            "delete": {
                "description": "Delete an image file by id",
                "consumes": [
                    "application/json"
                ],
                "produces": [
                    "application/json"
                ],
                "tags": [
                    "images"
                ],
                "summary": "Delete an image",
                "parameters": [
                    {
                        "type": "string",
                        "description": "id of the image to delete",
                        "name": "id",
                        "in": "path",
                        "required": true
                    }
                ],
                "responses": {}
            }
        }
    }
}